compextAI/__init__.py
compextAI/default_tools.py
compextAI/execution.py
compextAI/messages.py
compextAI/params.py
compextAI/threads.py
compextAI/tools.py
compextAI/utils.py
compextAI/api/api.py
CompextAI-0.0.37.dist-info/LICENSE
CompextAI-0.0.37.dist-info/METADATA
CompextAI-0.0.37.dist-info/WHEEL
CompextAI-0.0.37.dist-info/top_level.txt
CompextAI-0.0.37.dist-info/RECORD
