Metadata-Version: 2.2
Name: CompextAI
Version: 0.0.37
Summary: Python client for CompextAI
Author-email: burnerlee <avi.aviral140@gmail.com>
Project-URL: Homepage, https://github.com/burnerlee/compextAI
Project-URL: Issues, https://github.com/burnerlee/compextAI/issues
Classifier: Programming Language :: Python :: 3
Classifier: License :: OSI Approved :: MIT License
Classifier: Operating System :: OS Independent
Requires-Python: >=3.8
License-File: LICENSE
